abstractframework/__init__.py
abstractframework-0.1.0.dist-info/licenses/LICENSE
abstractframework-0.1.0.dist-info/METADATA
abstractframework-0.1.0.dist-info/WHEEL
abstractframework-0.1.0.dist-info/top_level.txt
abstractframework-0.1.0.dist-info/RECORD
