Metadata-Version: 2.4
Name: abstractframework
Version: 0.1.0
Summary: A unified ecosystem for AI-powered applications and intelligent systems
Author-email: Laurent-Philippe Albou <contact@abstractcore.ai>
Maintainer-email: Laurent-Philippe Albou <contact@abstractcore.ai>
License: MIT License
Project-URL: Homepage, https://github.com/lpalbou/AbstractFramework
Project-URL: Documentation, https://github.com/lpalbou/AbstractFramework
Project-URL: Repository, https://github.com/lpalbou/AbstractFramework
Project-URL: Bug Tracker, https://github.com/lpalbou/AbstractFramework/issues
Project-URL: Changelog, https://github.com/lpalbou/AbstractFramework/blob/main/CHANGELOG.md
Project-URL: AbstractCore, https://github.com/lpalbou/AbstractCore
Keywords: ai,llm,agents,memory,swarm,artificial-intelligence,machine-learning,nlp,chatbot,framework,ecosystem
Classifier: Development Status :: 3 - Alpha
Classifier: Intended Audience :: Developers
Classifier: Intended Audience :: Science/Research
Classifier: License :: OSI Approved :: MIT License
Classifier: Operating System :: OS Independent
Classifier: Programming Language :: Python :: 3
Classifier: Programming Language :: Python :: 3.8
Classifier: Programming Language :: Python :: 3.9
Classifier: Programming Language :: Python :: 3.10
Classifier: Programming Language :: Python :: 3.11
Classifier: Programming Language :: Python :: 3.12
Classifier: Topic :: Scientific/Engineering :: Artificial Intelligence
Classifier: Topic :: Software Development :: Libraries :: Python Modules
Classifier: Topic :: System :: Distributed Computing
Requires-Python: >=3.8
License-File: LICENSE
Provides-Extra: core
Requires-Dist: abstractcore[all]>=2.4.0; extra == "core"
Provides-Extra: memory
Requires-Dist: abstractmemory>=0.1.0; extra == "memory"
Provides-Extra: agent
Requires-Dist: abstractagent>=0.1.0; extra == "agent"
Provides-Extra: swarm
Requires-Dist: abstractswarm>=0.1.0; extra == "swarm"
Provides-Extra: available
Requires-Dist: abstractcore[all]>=2.4.0; extra == "available"
Provides-Extra: all
Requires-Dist: abstractcore[all]>=2.4.0; extra == "all"
Provides-Extra: dev
Requires-Dist: pytest>=7.0.0; extra == "dev"
Requires-Dist: pytest-cov>=4.0.0; extra == "dev"
Requires-Dist: black>=23.0.0; extra == "dev"
Requires-Dist: isort>=5.12.0; extra == "dev"
Requires-Dist: flake8>=6.0.0; extra == "dev"
Requires-Dist: mypy>=1.0.0; extra == "dev"
Requires-Dist: pre-commit>=3.0.0; extra == "dev"
Provides-Extra: docs
Requires-Dist: mkdocs>=1.5.0; extra == "docs"
Requires-Dist: mkdocs-material>=9.0.0; extra == "docs"
Requires-Dist: mkdocstrings[python]>=0.20.0; extra == "docs"
Dynamic: license-file
